pointercratecli/__init__.py
pointercratecli/demonlistSearch.py
pointercratecli/demonlistSearchNoRich.py
pointercratecli/getListSize.py
pointercratecli/getTopPlayers.py
pointercratecli/getTopXDemons.py
pointercratecli/main.py
pointercratecli/roulette.py
pointercratecli-0.0.3.dist-info/LICENSE
pointercratecli-0.0.3.dist-info/METADATA
pointercratecli-0.0.3.dist-info/WHEEL
pointercratecli-0.0.3.dist-info/top_level.txt
pointercratecli-0.0.3.dist-info/RECORD
